effortless/__init__.py
effortless/configuration.py
effortless/effortless.py
effortless/search.py
effortless-1.3.2.dist-info/licenses/LICENSE
tests/__init__.py
tests/test_advanced_usage.py
tests/test_configuration.py
tests/test_docs.py
tests/test_effortless_usage.py
tests/test_encryption.py
tests/test_remove.py
tests/test_search.py
tests/test_update.py
effortless-1.3.2.dist-info/METADATA
effortless-1.3.2.dist-info/WHEEL
effortless-1.3.2.dist-info/top_level.txt
effortless-1.3.2.dist-info/RECORD
