Metadata-Version: 2.4
Name: Effortless
Version: 1.3.2
Summary: Databases should be Effortless.
Home-page: https://effortless.bboonstra.dev/
Author: Ben Boonstra
Author-email: ben@bboonstra.dev
License: MIT
Project-URL: Bug Tracker, https://github.com/bboonstra/Effortless/issues
Project-URL: Documentation, https://effortless.bboonstra.dev
Project-URL: Source Code, https://github.com/bboonstra/Effortless
Keywords: database,effortless,simple storage,beginner,easy,db
Classifier: Programming Language :: Python :: 3
Classifier: License :: OSI Approved :: MIT License
Classifier: Operating System :: OS Independent
Classifier: Development Status :: 4 - Beta
Classifier: Intended Audience :: Developers
Classifier: Intended Audience :: Education
Classifier: Natural Language :: English
Classifier: Topic :: Database
Classifier: Topic :: Software Development :: Libraries :: Python Modules
Classifier: Topic :: Database :: Database Engines/Servers
Classifier: Topic :: Software Development :: Libraries :: Application Frameworks
Requires-Python: >=3.9
License-File: LICENSE
Requires-Dist: cryptography>=41.0.0
Dynamic: author
Dynamic: author-email
Dynamic: classifier
Dynamic: description
Dynamic: description-content-type
Dynamic: home-page
Dynamic: keywords
Dynamic: license
Dynamic: license-file
Dynamic: project-url
Dynamic: requires-dist
Dynamic: requires-python
Dynamic: summary
